Metadata-Version: 2.4
Name: adafruit-circuitpython-uc8151d
Version: 2.0.3
Summary: CircuitPython `displayio` driver for US8151D-based ePaper displays
Author-email: Adafruit Industries <circuitpython@adafruit.com>
License: MIT
Project-URL: Homepage, https://github.com/adafruit/Adafruit_CircuitPython_UC8151D.git
Keywords: adafruit,blinka,circuitpython,micropython,uc8151d,uc8151,us8151d,displayio,epd,epaper,flexible
Classifier: Intended Audience :: Developers
Classifier: Topic :: Software Development :: Libraries
Classifier: Topic :: Software Development :: Embedded Systems
Classifier: Topic :: System :: Hardware
Classifier: License :: OSI Approved :: MIT License
Classifier: Programming Language :: Python :: 3
License-File: LICENSE
Requires-Dist: Adafruit-Blinka
Requires-Dist: adafruit-blinka-displayio
Provides-Extra: optional
Dynamic: license-file
